uniconvert/__init__.py
uniconvert/base_converters.py
uniconvert/converters.py
uniconvert/img_converter.py
uniconvert/utils.py
uniconvert/video_converter.py
UniConvert-0.2.dist-info/METADATA
UniConvert-0.2.dist-info/WHEEL
UniConvert-0.2.dist-info/top_level.txt
UniConvert-0.2.dist-info/RECORD
